sablier/__init__.py
sablier/auth.py
sablier/client.py
sablier/data_collector.py
sablier/exceptions.py
sablier/feature_set.py
sablier/http_client.py
sablier/user_settings.py
sablier/model/__init__.py
sablier/model/builder.py
sablier/model/manager.py
sablier/model/validators.py
sablier/portfolio/__init__.py
sablier/portfolio/builder.py
sablier/portfolio/manager.py
sablier/portfolio/optimizer.py
sablier/portfolio/test.py
sablier/project/__init__.py
sablier/project/builder.py
sablier/project/manager.py
sablier/scenario/__init__.py
sablier/scenario/builder.py
sablier/scenario/manager.py
sablier_sdk-0.1.2.dist-info/licenses/LICENSE
sablier_sdk-0.1.2.dist-info/METADATA
sablier_sdk-0.1.2.dist-info/WHEEL
sablier_sdk-0.1.2.dist-info/top_level.txt
sablier_sdk-0.1.2.dist-info/RECORD
