Metadata-Version: 2.4
Name: sablier-sdk
Version: 0.1.2
Summary: Python SDK for Sablier Market Scenario Generator - Create scenario-conditioned synthetic financial data
Author: Sablier Team
License-Expression: MIT
Project-URL: Repository, https://github.com/michu5696/sablier-sdk
Project-URL: Issues, https://github.com/michu5696/sablier-sdk/issues
Keywords: finance,synthetic-data,scenarios,quantitative-finance,machine-learning
Classifier: Development Status :: 3 - Alpha
Classifier: Intended Audience :: Financial and Insurance Industry
Classifier: Intended Audience :: Science/Research
Classifier: Programming Language :: Python :: 3
Classifier: Programming Language :: Python :: 3.9
Classifier: Programming Language :: Python :: 3.10
Classifier: Programming Language :: Python :: 3.11
Classifier: Programming Language :: Python :: 3.12
Classifier: Topic :: Scientific/Engineering
Classifier: Topic :: Office/Business :: Financial
Requires-Python: >=3.8
License-File: LICENSE
Requires-Dist: requests>=2.28.0
Requires-Dist: pandas>=1.5.0
Requires-Dist: numpy>=1.23.0
Requires-Dist: pydantic>=2.0.0
Requires-Dist: python-dateutil>=2.8.0
Requires-Dist: matplotlib>=3.5.0
Requires-Dist: scikit-optimize>=0.9.0
Requires-Dist: jinja2>=3.0.0
Provides-Extra: viz
Requires-Dist: seaborn>=0.12.0; extra == "viz"
Requires-Dist: plotly>=5.0.0; extra == "viz"
Provides-Extra: stats
Requires-Dist: scipy>=1.11.0; extra == "stats"
Requires-Dist: statsmodels>=0.14.0; extra == "stats"
Provides-Extra: dev
Requires-Dist: pytest>=7.0.0; extra == "dev"
Requires-Dist: pytest-cov>=4.0.0; extra == "dev"
Requires-Dist: black>=22.0.0; extra == "dev"
Requires-Dist: mypy>=1.0.0; extra == "dev"
Requires-Dist: ruff>=0.1.0; extra == "dev"
Provides-Extra: all
Requires-Dist: sablier-sdk[dev,stats,viz]; extra == "all"
Dynamic: license-file
